hfstol/__init__.py
hfstol/constants.py
hfstol/main.py
hfstol/shared.py
hfstol/transducer.py
hfstol-1.2.11.dist-info/LICENSE
hfstol-1.2.11.dist-info/METADATA
hfstol-1.2.11.dist-info/WHEEL
hfstol-1.2.11.dist-info/entry_points.txt
hfstol-1.2.11.dist-info/top_level.txt
hfstol-1.2.11.dist-info/RECORD
