Metadata-Version: 2.1
Name: hfstol
Version: 1.2.11
Summary: hfst optimised lookup reimplemented in python. Including a wrapper to the original hfst-optimized-lookup
Home-page: https://github.com/Madoshakalaka/hfstol
Author: Matt Yan
Author-email: syan4@ualberta.ca
License: UNKNOWN
Project-URL: Bug Reports, https://github.com/Madoshakalaka/hfstol/issues
Project-URL: Funding, https://github.com/Madoshakalaka/hfstol
Project-URL: Say Thanks!, https://github.com/Madoshakalaka/hfstol
Project-URL: Source, https://github.com/Madoshakalaka/hfstol
Platform: UNKNOWN
Classifier: Development Status :: 3 - Alpha
Classifier: Intended Audience :: Developers
Classifier: Topic :: Software Development :: Build Tools
Classifier: License :: OSI Approved :: MIT License
Classifier: Programming Language :: Python :: 3.5
Classifier: Programming Language :: Python :: 3.6
Classifier: Programming Language :: Python :: 3.7
Requires-Python: >=3.5
